{
    "_id": "network",
    "network": {
      "metadata": {
        "node_types": ["Websites", "Contacts", "Devices"],
        "categories": [
          "Research & Reference",
          "Conference Events",
          "Networking",
          "Utility",
          "Personal"
        ],
        "review_statuses": ["Pending", "Reviewed", "Not Suitable"]
      },
      "data": {
        "websites": {
          "metadata": {
            "categories": ["Research & Reference", "Conference Events"],
            "review_statuses": ["Pending", "Reviewed"]
          },
          "data": [
            {
              "_id": "1",
              "url": "https://www.google.com/search?q=CES+2024+keynote+speakers",
              "description": "CES 2024 Keynote Speakers",
              "usefulness_description": "Find information on the keynote speakers at CES 2024.",
              "category": "Conference Events",
              "review_status": "Pending",
              "thumbnail_url": "https://images.pexels.com/photos/326514/pexels-photo-326514.jpeg?auto=compress&cs=tinysrgb&w=1260&h=750&dpr=1"
            },
            {
              "_id": "2",
              "url": "https://www.google.com/search?q=latest+tech+trends+CES+2024",
              "description": "Latest Tech Trends at CES 2024",
              "usefulness_description": "Explore the latest technology trends and innovations showcased at CES 2024.",
              "category": "Research & Reference",
              "review_status": "Pending",
              "thumbnail_url": "https://images.pexels.com/photos/326514/pexels-photo-326514.jpeg?auto=compress&cs=tinysrgb&w=1260&h=750&dpr=1"
            }
          ]
        },
        "contacts": {
          "metadata": {
            "categories": ["Networking", "Personal"],
            "review_statuses": ["Reviewed", "Not Suitable"]
          },
          "data": [
            {
              "_id": "3",
              "name": "Alice Johnson",
              "email": "alice.johnson@ces.com",
              "phone": "123-456-7890",
              "relationship": "Conference Organizer",
              "category": "Networking",
              "review_status": "Reviewed",
              "thumbnail_url": "https://images.pexels.com/photos/267389/pexels-photo-267389.jpeg?auto=compress&cs=tinysrgb&w=1260&h=750&dpr=1"
            },
            {
              "_id": "4",
              "name": "Bob Brown",
              "email": "bob.brown@startup.com",
              "phone": "987-654-3210",
              "relationship": "Startup Founder",
              "category": "Networking",
              "review_status": "Reviewed",
              "thumbnail_url": "https://images.pexels.com/photos/267389/pexels-photo-267389.jpeg?auto=compress&cs=tinysrgb&w=1260&h=750&dpr=1"
            }
          ]
        },
        "devices": {
          "metadata": {
            "categories": ["Utility"],
            "review_statuses": ["Pending", "Reviewed"]
          },
          "data": [
            {
              "_id": "5",
              "name": "AR Glasses",
              "type": "Glasses",
              "location": "CES Exhibit Hall",
              "api_info": {
                "url": "https://api.example.com/arglasses",
                "auth_token": "XXXXXXXXXXXXXXXX"
              },
              "category": "Utility",
              "review_status": "Reviewed",
              "thumbnail_url": "https://images.unsplash.com/photo-1605465155444-5f084e5ec10a?q=80&w=2070&auto=format&fit=crop&ixlib=rb-4.0.3&ixid=M3wxMjA3fDB8MHxwaG90by1wYWdlfHx8fGVufDB8fHx8fA%3D%3D"
            },
            {
              "_id": "6",
              "name": "Smart Badge",
              "type": "Badge",
              "location": "CES Main Entrance",
              "api_info": {
                "url": "https://api.example.com/smartbadge",
                "auth_token": "YYYYYYYYYYYYYYYY"
              },
              "category": "Utility",
              "review_status": "Pending",
              "thumbnail_url": "https://images.unsplash.com/photo-1605465155444-5f084e5ec10a?q=80&w=2070&auto=format&fit=crop&ixlib=rb-4.0.3&ixid=M3wxMjA3fDB8MHxwaG90by1wYWdlfHx8fGVufDB8fHx8fA%3D%3D"
            }
          ]
        }
      }
    }
  }  